COPYING
MANIFEST.in
NEWS
README
setup.cfg
setup.py
PyHurd.egg-info/PKG-INFO
PyHurd.egg-info/SOURCES.txt
PyHurd.egg-info/dependency_links.txt
PyHurd.egg-info/requires.txt
PyHurd.egg-info/top_level.txt
examples/copy.py
examples/dump.py
examples/file.py
pyhurd/__init__.py
pyhurd/gnu_source.h
pyhurd/pyhurd.fcntl.c
pyhurd/pyhurd.fcntl.pxd
pyhurd/pyhurd.fcntl.py
pyhurd/pyhurd.glibc.c
pyhurd/pyhurd.glibc.pxd
pyhurd/pyhurd.glibc.py
pyhurd/pyhurd.hurd.c
pyhurd/pyhurd.hurd.pxd
pyhurd/pyhurd.hurd.py
pyhurd/pyhurd.mach.c
pyhurd/pyhurd.mach.pxd
pyhurd/pyhurd.mach.py
test/__init__.py
test/test_io.py