Metadata-Version: 1.0
Name: PyHurd
Version: 0.0.0a5
Summary: Pytonish GNU/Hurd
Home-page: http://savannah.nongnu.org/projects/pyhurd/
Author: Anatoly A. Kazantsev
Author-email: anatoly@gnu.org
License: GNU GPL2
Download-URL: http://pypi.python.org/pypi/PyHurd/
Platform: UNKNOWN
Classifier: Development Status :: 1 - Planning
Classifier: Environment :: Console
Classifier: Environment :: Other Environment
Classifier: Intended Audience :: Developers
Classifier: License :: OSI Approved :: GNU General Public License (GPL)
Classifier: Natural Language :: English
Classifier: Operating System :: POSIX :: GNU Hurd
Classifier: Programming Language :: Python
Classifier: Topic :: Software Development :: Libraries :: Python Modules
Classifier: Topic :: System :: Operating System Kernels :: GNU Hurd
